{"__type":"Skyline.DataMiner.Web.Common.v1.Dashboards.DMADashboardConfig","IsApplicationPage":false,"Version":4,"Revision":10,"Name":"af2bd542-aa37-461d-b1a9-7a390cb2507c","Folder":"","Description":null,"CreatedBy":"SKYLINE2\\RobbeDG","ModifiedBy":"SKYLINE2\\RobbeDG","TimeCreatedUTC":1731503010952,"TimeModifiedUTC":1731503486531,"Data":[{"__type":"Skyline.DataMiner.Web.Common.v1.Dashboards.DMADashboardDataInstance","ID":1,"Data":{"__type":"Skyline.DataMiner.Web.Common.v1.Dashboards.DMADashboardQueryData","QueryID":"76dd43bf-d279-4dec-8a34-20a9e5a0b641","Query":{"__type":"Skyline.DataMiner.Web.Common.v1.DMAGenericInterfaceQuery","ID":"Custom data","Options":[{"__type":"Skyline.DataMiner.Web.Common.v1.DMAGenericInterfaceQueryChosenOption","Type":"string","ID":"Data source","Value":{"__type":"Skyline.DataMiner.Web.Common.v1.DMAPrimitiveValue","Value":"{\"DataSourceInterface\":\"Skyline.DataMiner.Analytics.GenericInterface.IGQIDataSource\",\"ScriptName\":\"Element Home Agents\",\"LibraryName\":\"Element Home Agents\",\"TypeFullName\":\"Element_Home_Agents_1.ElementHomeAgents\",\"TypeName\":\"ElementHomeAgents\"}","Type":"string","IsNull":false}}],"Child":{"__type":"Skyline.DataMiner.Web.Common.v1.DMAGenericInterfaceQuery","ID":"Custom data arguments","Options":[{"__type":"Skyline.DataMiner.Web.Common.v1.DMAGenericInterfaceQueryChosenOption","Type":null,"ID":"Arguments","Value":[]}],"Child":null,"Version":65536,"Guid":null,"Name":null,"NodeKey":"bd317059-28e8-42ab-b3eb-861bb7baef7e"},"Version":65536,"Guid":"76dd43bf-d279-4dec-8a34-20a9e5a0b641","Name":"Element Home Agents","NodeKey":"b1f3b027-fca2-4d6e-99e3-20cfdfb91a2d"},"DataVersion":0,"Features":3,"ID":"Query/76dd43bf-d279-4dec-8a34-20a9e5a0b641","DisplayName":"Element Home Agents","Type":"Query"}},{"__type":"Skyline.DataMiner.Web.Common.v1.Dashboards.DMADashboardDataInstance","ID":2,"Data":{"__type":"Skyline.DataMiner.Web.Common.v1.Dashboards.DMADashboardQueryColumnData","Query":"76dd43bf-d279-4dec-8a34-20a9e5a0b641","ColumnID":"b1f3b027-fca2-4d6e-99e3-20cfdfb91a2d_Element Name","Name":null,"Hidden":false,"DataVersion":1,"Features":3,"ID":"Query column/76dd43bf-d279-4dec-8a34-20a9e5a0b641/b1f3b027-fca2-4d6e-99e3-20cfdfb91a2d_Element Name","DisplayName":"Element Name","Type":"Query column"}},{"__type":"Skyline.DataMiner.Web.Common.v1.Dashboards.DMADashboardDataInstance","ID":3,"Data":{"__type":"Skyline.DataMiner.Web.Common.v1.Dashboards.DMADashboardQueryColumnData","Query":"76dd43bf-d279-4dec-8a34-20a9e5a0b641","ColumnID":"b1f3b027-fca2-4d6e-99e3-20cfdfb91a2d_Home Agent Name","Name":null,"Hidden":false,"DataVersion":1,"Features":3,"ID":"Query column/76dd43bf-d279-4dec-8a34-20a9e5a0b641/b1f3b027-fca2-4d6e-99e3-20cfdfb91a2d_Home Agent Name","DisplayName":"Home Agent Name","Type":"Query column"}}],"ThemeKey":"Skyline Light - Gray","Theme":null,"Settings":{"__type":"Skyline.DataMiner.Web.Common.v1.Dashboards.DMADashboardSettings","ComponentShift":false,"UseDynamicUnits":true,"FitToView":false,"VirtualizeComponents":true},"Rows":null,"Components":[{"__type":"Skyline.DataMiner.Web.Common.v1.Dashboards.DMADashboardComponent","ID":1,"Title":null,"Type":"generic-data","Version":6,"DataIDs":[1],"FilterIDs":[2,3],"GroupIDs":[],"Triggers":null,"Visualization":"generic-table","VisualizationVersion":1,"Features":1,"VisualizationFeatures":1,"Size":4,"Style":null,"StyleSettings":null,"Theme":null,"Position":{"__type":"Skyline.DataMiner.Web.Common.v1.Dashboards.DMADashboardComponentPosition","X":0,"Y":0,"Rows":62,"Cols":24},"InputData":{"displayQueryName":true,"columnFilters":{},"pieChartDims":{"label":null,"size":null,"color":null},"barChartDims":{"label":null,"bars":null},"schedulerDims":[],"tableTemplates":{},"mapsLayerSettings":[{"id":0,"name":"Layer","weight":1,"queries":[],"dataSettings":{}}],"overrideDynamicUnits":false,"useDynamicUnits":false,"receiveUpdates":false,"tableQueriesSettings":[],"initialSelection":false,"noResultsMessage":"Nothing to show.","showQuickFilter":true,"volatileSettings":{"colors":{}}},"AllowWebSockets":false,"PollingInterval":0,"FeedDefaults":null,"WebSocketSettings":{"__type":"Skyline.DataMiner.Web.Common.v1.Dashboards.DMADashboardWebSocketSettings","Inherit":true,"AllowWebSockets":false,"PollingInterval":0}}],"DefaultTimeFilter":{"__type":"Skyline.DataMiner.Web.Common.v1.Dashboards.DMADashboardTimeFilter","Type":null},"UseTimeFilter":false,"WebSocketConfig":{"__type":"Skyline.DataMiner.Web.Common.v1.Dashboards.DMAWebSocketConfig","AllowWebSockets":true,"FastPollingInterval":5000,"SlowPollingInterval":300000},"DashboardRequirements":{"__type":"Skyline.DataMiner.Web.Common.v1.Dashboards.DMADashboardRequirements","CPEs":null,"Elements":null,"Indices":null,"Parameters":null,"Protocols":null,"RedundancyGroups":null,"SLAs":null,"Services":null,"TimeSpans":null,"Views":null},"DataPool":[],"Columns":24}